pyla_logger/__init__.py
pyla_logger/logger.py
pyla_logger/tests/__init__.py
pyla_logger/tests/test_logger.py
pyla_logger-1.2.1.dist-info/METADATA
pyla_logger-1.2.1.dist-info/WHEEL
pyla_logger-1.2.1.dist-info/top_level.txt
pyla_logger-1.2.1.dist-info/RECORD
