Metadata-Version: 2.4
Name: pyla-logger
Version: 1.2.1
Summary: Structured logging library for Python applications
Author: LangAdventure LLC
License: GPL-3.0
Project-URL: Homepage, https://github.com/langadventurellc/pyla-logger
Project-URL: Repository, https://github.com/langadventurellc/pyla-logger
Project-URL: Issues, https://github.com/langadventurellc/pyla-logger/issues
Keywords: logging,structured-logging,python,langadventure
Classifier: Development Status :: 4 - Beta
Classifier: Intended Audience :: Developers
Classifier: License :: OSI Approved :: GNU General Public License v3 (GPLv3)
Classifier: Programming Language :: Python :: 3
Classifier: Programming Language :: Python :: 3.12
Classifier: Topic :: Software Development :: Libraries :: Python Modules
Classifier: Topic :: System :: Logging
Requires-Python: >=3.12
Requires-Dist: structlog>=25.4.0
Provides-Extra: dev
Requires-Dist: black; extra == "dev"
Requires-Dist: flake8; extra == "dev"
Requires-Dist: flake8-pyproject; extra == "dev"
Requires-Dist: isort; extra == "dev"
Requires-Dist: pyright; extra == "dev"
Requires-Dist: pytest; extra == "dev"
Requires-Dist: pytest-mock; extra == "dev"
Requires-Dist: pre-commit; extra == "dev"
